cdk_cloudformation_github_teams_membership/__init__.py
cdk_cloudformation_github_teams_membership/py.typed
cdk_cloudformation_github_teams_membership/_jsii/__init__.py
cdk_cloudformation_github_teams_membership/_jsii/github-teams-membership@1.6.0-alpha.7.jsii.tgz
cdk_cloudformation_github_teams_membership-1.6.0a7.dist-info/LICENSE
cdk_cloudformation_github_teams_membership-1.6.0a7.dist-info/METADATA
cdk_cloudformation_github_teams_membership-1.6.0a7.dist-info/WHEEL
cdk_cloudformation_github_teams_membership-1.6.0a7.dist-info/top_level.txt
cdk_cloudformation_github_teams_membership-1.6.0a7.dist-info/RECORD
